README.md
setup.cfg
setup.py
super_puper_python_package/__init__.py
super_puper_python_package.egg-info/PKG-INFO
super_puper_python_package.egg-info/SOURCES.txt
super_puper_python_package.egg-info/dependency_links.txt
super_puper_python_package.egg-info/requires.txt
super_puper_python_package.egg-info/top_level.txt